{"version":1,"source":"official_marketplace_json","itemHrid":"/items/burble_shears","variant":2,"earliestTime":1774881066,"latestTime":1775587072,"rows":[{"time":1774881066,"a":245000,"b":-1,"p":null,"v":null,"source":"official_hourly"},{"time":1774946264,"a":245000,"b":-1,"p":null,"v":null,"source":"official_hourly"},{"time":1774949884,"a":245000,"b":-1,"p":null,"v":null,"source":"official_hourly"},{"time":1775561766,"a":220000,"b":-1,"p":20000,"v":1},{"time":1775568961,"a":220000,"b":-1,"p":null,"v":null},{"time":1775572346,"a":220000,"b":-1,"p":null,"v":null},{"time":1775575871,"a":220000,"b":-1,"p":null,"v":null},{"time":1775583421,"a":220000,"b":-1,"p":null,"v":null},{"time":1775587072,"a":220000,"b":-1,"p":null,"v":null}]}
